dgenies/__init__.py
dgenies/allowed_extensions.py
dgenies/config_reader.py
dgenies/database.py
dgenies/tools.py
dgenies/views.py
dgenies/bin/all_prepare.py
dgenies/bin/clean_jobs.py
dgenies/bin/filter_contigs.py
dgenies/bin/index.py
dgenies/bin/local_scheduler.py
dgenies/bin/mashmap
dgenies/bin/merge_splitted_chrms.py
dgenies/bin/minimap2
dgenies/bin/minimap_to_json.py
dgenies/bin/sort_paf.py
dgenies/bin/split_fa.py
dgenies/bin/start_local_scheduler.sh
dgenies/lib/__init__.py
dgenies/lib/crons.py
dgenies/lib/datafile.py
dgenies/lib/decorators.py
dgenies/lib/drmaasession.py
dgenies/lib/exceptions.py
dgenies/lib/functions.py
dgenies/lib/job_manager.py
dgenies/lib/latest.py
dgenies/lib/mailer.py
dgenies/lib/paf.py
dgenies/lib/parsers.py
dgenies/lib/upload_file.py
dgenies/lib/validators.py
dgenies/lib/mail_templates/batch_job_notification.html
dgenies/lib/mail_templates/dl_fasta.html
dgenies/lib/mail_templates/job_notification.html
dgenies/md/INSTALL.md
dgenies/md/cookies.md
dgenies/md/doc_definitions.md
dgenies/md/doc_dotplot.md
dgenies/md/doc_formats.md
dgenies/md/doc_run.md
dgenies/md/lorem_ipsum.md
dgenies/md/user_manual.md
dgenies/static/css/animate.css
dgenies/static/css/bootstrap.min.css
dgenies/static/css/bootstrap.min.css.map
dgenies/static/css/chosen.min.css
dgenies/static/css/dgenies-offline-result.min.css
dgenies/static/css/dgenies.css
dgenies/static/css/dgenies.min.css
dgenies/static/css/jquery-ui.min.css
dgenies/static/css/jquery.modal.min.css
dgenies/static/css/katex.min.css
dgenies/static/css/codemirror/codemirror.css
dgenies/static/css/codemirror/lint.css
dgenies/static/css/images/chosen-sprite.png
dgenies/static/css/images/chosen-sprite@2x.png
dgenies/static/css/images/loading-cascade.gif
dgenies/static/css/images/loading1.gif
dgenies/static/css/images/logo.svg
dgenies/static/css/images/reset.svg
dgenies/static/css/images/reset_hover.svg
dgenies/static/css/images/success.svg
dgenies/static/css/images/ui-bg_diagonal-maze_20_6e4f1c_10x10.png
dgenies-1.5.0.dist-info/LICENSE.txt
dgenies-1.5.0.dist-info/METADATA
dgenies-1.5.0.dist-info/WHEEL
dgenies-1.5.0.dist-info/top_level.txt
dgenies-1.5.0.dist-info/RECORD
