Metadata-Version: 2.1
Name: dgenies
Version: 1.5.0
Summary: Dotplot large Genomes in an Interactive, Efficient and Simple way
Home-page: http://dgenies.toulouse.inra.fr
Author: Floreal Cabanettes
Author-email: floreal.cabanettes@inra.fr
Maintainer: Philippe Bordron
Maintainer-email: philippe.bordron@inrae.fr
Project-URL: Sources, https://github.com/genotoul-bioinfo/dgenies
Project-URL: Bug Tracker, https://github.com/genotoul-bioinfo/dgenies/issues
Project-URL: Changelog, https://github.com/genotoul-bioinfo/dgenies/blob/master/CHANGELOG.md
Project-URL: Wiki, https://github.com/genotoul-bioinfo/dgenies/wiki
Keywords: bioinformatics,genome,comparison,dotplot,inrae,genotoul
Classifier: Development Status :: 5 - Production/Stable
Classifier: Environment :: Web Environment
Classifier: Framework :: Flask
Classifier: Intended Audience :: Education
Classifier: Intended Audience :: Science/Research
Classifier: License :: OSI Approved :: GNU General Public License v3 (GPLv3)
Classifier: Operating System :: Microsoft :: Windows
Classifier: Operating System :: POSIX
Classifier: Programming Language :: JavaScript
Classifier: Programming Language :: Python :: 3
Classifier: Programming Language :: Python :: 3.5
Classifier: Programming Language :: Python :: 3.6
Classifier: Programming Language :: Python :: 3.7
Classifier: Programming Language :: Python :: 3.8
Classifier: Programming Language :: Python :: 3.9
Classifier: Programming Language :: Python :: 3.10
Classifier: Topic :: Scientific/Engineering :: Bio-Informatics
License-File: LICENSE.txt
Requires-Dist: Flask (>=2)
Requires-Dist: Jinja2
Requires-Dist: numpy
Requires-Dist: requests (>=2.20.1)
Requires-Dist: biopython (>=1.70)
Requires-Dist: psutil (>=5.6.6)
Requires-Dist: tendo (>=0.2)
Requires-Dist: matplotlib (>=2.1)
Requires-Dist: intervaltree (==3.*)
Requires-Dist: Markdown (>=2.6)
Requires-Dist: pyyaml (>=5.4.1)
Requires-Dist: werkzeug (>=2)
Requires-Dist: xopen (>=1.0)
Requires-Dist: Flask-Mail (==0.9.*)
Requires-Dist: peewee (==3.*)
Requires-Dist: python-crontab (==2.*,>=2.2)
Requires-Dist: drmaa (==0.7.*)
